adviz/__init__.py
adviz/_modidx.py
adviz/core.py
adviz/ecdf.py
adviz/flag.py
adviz/racing_chart.py
adviz/serp_heatmap.py
adviz/status_codes.py
adviz/style_table.py
adviz/url_structure.py
adviz/value_counts.py
adviz/value_counts_plus.py
adviz-0.0.25.dist-info/licenses/LICENSE
adviz-0.0.25.dist-info/METADATA
adviz-0.0.25.dist-info/WHEEL
adviz-0.0.25.dist-info/entry_points.txt
adviz-0.0.25.dist-info/top_level.txt
adviz-0.0.25.dist-info/RECORD
