Metadata-Version: 2.4
Name: adviz
Version: 0.0.25
Summary: advertools visualizations
Home-page: https://github.com/eliasdabbas/adviz
Author: Elias Dabbas
Author-email: eliasdabbas@gmail.com
License: Apache Software License 2.0
Keywords: nbdev jupyter notebook python
Classifier: Development Status :: 4 - Beta
Classifier: Intended Audience :: Developers
Classifier: Natural Language :: English
Classifier: Programming Language :: Python :: 3.7
Classifier: Programming Language :: Python :: 3.8
Classifier: Programming Language :: Python :: 3.9
Classifier: Programming Language :: Python :: 3.10
Classifier: License :: OSI Approved :: Apache Software License
Requires-Python: >=3.7
License-File: LICENSE
Requires-Dist: pandas
Requires-Dist: matplotlib
Requires-Dist: advertools
Requires-Dist: plotly>=6.0.0
Requires-Dist: jinja2
Requires-Dist: dash_bootstrap_templates
Provides-Extra: dev
Requires-Dist: nbformat; extra == "dev"
Requires-Dist: kaleido; extra == "dev"
Dynamic: author
Dynamic: author-email
Dynamic: classifier
Dynamic: description
Dynamic: description-content-type
Dynamic: home-page
Dynamic: keywords
Dynamic: license
Dynamic: license-file
Dynamic: provides-extra
Dynamic: requires-dist
Dynamic: requires-python
Dynamic: summary
